Metadata-Version: 1.1
Name: py-cpuinfo
Version: 6.0.0
Summary: Get CPU info with pure Python 2 & 3
Home-page: https://github.com/workhorsy/py-cpuinfo
Author: Matthew Brennan Jones
Author-email: matthew.brennan.jones@gmail.com
License: MIT
Platform: UNKNOWN
Classifier: Development Status :: 5 - Production/Stable
Classifier: Topic :: Utilities
Classifier: License :: OSI Approved :: MIT License
Classifier: Programming Language :: Python :: 2.7
Classifier: Programming Language :: Python :: 3
